{
  "chapter_num": "11",
  "chapter_title": "The Null Value Principle",
  "word_count": 3501,
  "top_keywords": [
    [
      "response",
      83
    ],
    [
      "her",
      40
    ],
    [
      "non",
      36
    ],
    [
      "strategic",
      35
    ],
    [
      "energy",
      27
    ],
    [
      "s",
      21
    ],
    [
      "had",
      19
    ],
    [
      "she",
      19
    ],
    [
      "while",
      19
    ],
    [
      "automatic",
      17
    ],
    [
      "t",
      16
    ],
    [
      "than",
      16
    ],
    [
      "research",
      16
    ],
    [
      "university",
      16
    ],
    [
      "effectiveness",
      16
    ]
  ],
  "potential_quotes": [
    "Her finger hovered over the keyboard.",
    "Rivera had clarified that strategic non-response wasn't about passivity\u2014it was about power optimization.",
    "Encouraged by this small success, Amara began applying strategic non-response more extensively.",
    "\"The space between stimulus and response contains your greatest power.",
    "By trying to draw her into an argument, he was seeking validation for his narrative that her success was somehow a mistake."
  ],
  "has_practical_application": true,
  "has_storytelling": true,
  "preview": "CHAPTER 11: THE NULL VALUE PRINCIPLE  Opening Story: \"The Provocation Optimization Failure\"  Amara's phone buzzed for the fifth time in twenty minutes. Each notification delivered another message from her former colleague, Marcus. The conversation had started with what seemed like a professional inquiry about project handover, but quickly devolved into thinly veiled criticism of her decision to leave the organization, followed by increasingly personal attacks on her career choices.  Her finger h...",
  "file_path": "/home/ubuntu/book_assessment/final_book_package/Chapter_11_The_Null_Value_Principle.docx"
}